databits/__init__.py
databits/loader/__init__.py
databits/loader/data.py
databits/model/__init__.py
databits/model/bert.py
databits/model/fasttext.py
databits/model/gru.py
databits/model/lstm.py
databits/model/module.py
databits/model/transformer.py
databits/trainer/__init__.py
databits/trainer/train.py
databits-2.0.5.dist-info/LICENSE
databits-2.0.5.dist-info/METADATA
databits-2.0.5.dist-info/WHEEL
databits-2.0.5.dist-info/top_level.txt
databits-2.0.5.dist-info/RECORD
